youmind_mcp/__init__.py
youmind_mcp/__main__.py
youmind_mcp/api_client.py
youmind_mcp/exceptions.py
youmind_mcp/server.py
youmind_mcp-0.0.1.dist-info/licenses/LICENSE
youmind_mcp-0.0.1.dist-info/METADATA
youmind_mcp-0.0.1.dist-info/WHEEL
youmind_mcp-0.0.1.dist-info/entry_points.txt
youmind_mcp-0.0.1.dist-info/top_level.txt
youmind_mcp-0.0.1.dist-info/RECORD
